snvannotators/__init__.py
snvannotators/cpraannotators/__init__.py
snvannotators/cpraannotators/cpragrch37annotator.py
snvannotators/hgvsplus/__init__.py
snvannotators/hgvsplus/annotators/__init__.py
snvannotators/hgvsplus/annotators/hgvsannotation.py
snvannotators/hgvsplus/annotators/hgvsgannotator.py
snvannotators/hgvsplus/annotators/hgvstpannotation.py
snvannotators/hgvsplus/creators/__init__.py
snvannotators/hgvsplus/creators/hgvspunknownposeditcreator.py
snvannotators/hgvsplus/creators/hgvspunknownposedittranscriptaccessioncreator.py
snvannotators/hgvsplus/creators/sequencevariantgcreator.py
snvannotators/hgvsplus/mappers/__init__.py
snvannotators/hgvsplus/mappers/hgvsctopmapper.py
snvannotators/hgvsplus/mappers/hgvsgtotmapper.py
snvannotators/hgvsplus/mappers/hgvsgtotpmapper.py
snvannotators/hgvsplus/models/__init__.py
snvannotators/hgvsplus/models/hgvsc.py
snvannotators/hgvsplus/models/hgvsg.py
snvannotators/hgvsplus/models/hgvsp.py
snvannotators/hgvsplus/models/hgvst.py
snvannotators/hgvsplus/parsers/__init__.py
snvannotators/hgvsplus/parsers/hgvsparser.py
snvannotators/myvariant/__init__.py
snvannotators/myvariant/annotation/__init__.py
snvannotators/myvariant/annotation/clinvar.py
snvannotators/myvariant/annotation/myvariantannotation.py
snvannotators/myvariant/annotation/gnomadallelefrequency/__init__.py
snvannotators/myvariant/annotation/gnomadallelefrequency/geneticancestrygroupallelefrequency.py
snvannotators/myvariant/annotation/gnomadallelefrequency/geneticancestrygroupnametolabelconverter.py
snvannotators/myvariant/annotation/gnomadallelefrequency/gnomadallelefrequency.py
snvannotators/myvariant/annotators/__init__.py
snvannotators/myvariant/annotators/myvariantcpraannotator.py
snvannotators/myvariant/annotators/myvarianthgvschrannotator.py
snvannotators/myvariant/annotators/myvarianthgvschrbatchannotator.py
snvannotators/oncokb/__init__.py
snvannotators/oncokb/oncokbcpraannotator.py
snvannotators/oncokb/oncokbcpragrch37annotator.py
snvannotators-0.0.3.dist-info/METADATA
snvannotators-0.0.3.dist-info/WHEEL
snvannotators-0.0.3.dist-info/top_level.txt
snvannotators-0.0.3.dist-info/RECORD
